pythonthesorimed/__init__.py
pythonthesorimed/api.py
pythonthesorimed/exceptions.py
pythonthesorimed/thesoitem.py
pythonthesorimed/parseur/__init__.py
pythonthesorimed/parseur/parseur.py
pythonthesorimed/parseur/prototype.py
pythonthesorimed-0.3.0.dist-info/METADATA
pythonthesorimed-0.3.0.dist-info/RECORD
pythonthesorimed-0.3.0.dist-info/WHEEL
pythonthesorimed-0.3.0.dist-info/entry_points.txt
pythonthesorimed-0.3.0.dist-info/pbr.json
pythonthesorimed-0.3.0.dist-info/top_level.txt
