Metadata-Version: 2.1
Name: pythonthesorimed
Version: 0.3.0
Summary: Une interface python avec la base médicamenteuse thesorimed
Home-page: https://github.com/jgirardet/pythonthesorimed
Author: Jimmy Girardet
Author-email: ijkl@netc.fr
License: UNKNOWN
Platform: UNKNOWN
Requires-Dist: pbr (>=3.0)
Requires-Dist: psycopg2-binary
Requires-Dist: yapf
